data_describe/__init__.py
data_describe/_version.py
data_describe/_widget.py
data_describe/backends/__init__.py
data_describe/backends/_backends.py
data_describe/backends/compute/__init__.py
data_describe/backends/compute/_modin/__init__.py
data_describe/backends/compute/_pandas/__init__.py
data_describe/backends/viz/__init__.py
data_describe/backends/viz/_plotly/__init__.py
data_describe/backends/viz/_pyLDAvis/__init__.py
data_describe/backends/viz/_seaborn/__init__.py
data_describe/compat/__init__.py
data_describe/compat/_dataframe.py
data_describe/compat/_dependency.py
data_describe/compat/_notebook.py
data_describe/config/__init__.py
data_describe/config/_config.py
data_describe/core/__init__.py
data_describe/core/clustering.py
data_describe/core/correlation.py
data_describe/core/distributions.py
data_describe/core/heatmap.py
data_describe/core/importance.py
data_describe/core/scatter.py
data_describe/core/summary.py
data_describe/core/time.py
data_describe/dimensionality_reduction/__init__.py
data_describe/dimensionality_reduction/dimensionality_reduction.py
data_describe/metrics/__init__.py
data_describe/metrics/bivariate.py
data_describe/metrics/univariate.py
data_describe/misc/__init__.py
data_describe/misc/colors.py
data_describe/misc/file_ext.py
data_describe/misc/load_data.py
data_describe/misc/logging.py
data_describe/misc/preprocessing.py
data_describe/privacy/__init__.py
data_describe/privacy/detection.py
data_describe/text/__init__.py
data_describe/text/text_preprocessing.py
data_describe/text/topic_modeling.py
examples/__init__.py
data_describe-0.1.0b3.dist-info/LICENSE
data_describe-0.1.0b3.dist-info/METADATA
data_describe-0.1.0b3.dist-info/WHEEL
data_describe-0.1.0b3.dist-info/entry_points.txt
data_describe-0.1.0b3.dist-info/top_level.txt
data_describe-0.1.0b3.dist-info/RECORD
