Metadata-Version: 2.1
Name: data-describe
Version: 0.1.0b3
Summary: A Pythonic EDA Accelerator for Data Science 
Home-page: https://data-describe.ai/
Author: https://github.com/data-describe/data-describe/graphs/contributors
Author-email: 
License: Apache-2.0
Project-URL: Bug Tracker, https://github.com/data-describe/data-describe/issues
Project-URL: Documentation, https://data-describe.ai/docs/master/
Project-URL: Source Code, https://github.com/data-describe/data-describe
Platform: UNKNOWN
Classifier: Programming Language :: Python
Classifier: Development Status :: 4 - Beta
Classifier: Programming Language :: Python :: 3.6
Classifier: Programming Language :: Python :: 3.7
Classifier: Programming Language :: Python :: 3.8
Classifier: Programming Language :: Python :: 3.9
Classifier: Programming Language :: Python :: Implementation :: PyPy
Requires-Python: >=3.6
Requires-Dist: pandas (>=1.0)
Requires-Dist: numpy (>=1.16)
Requires-Dist: scipy (>=1.1)
Requires-Dist: scikit-learn (>=0.23)
Requires-Dist: seaborn (>=0.11)
Requires-Dist: plotly (>=4.0)
Requires-Dist: importlib-metadata ; python_version <= "3.7"
Provides-Extra: all
Requires-Dist: modin (>=0.7.3) ; extra == 'all'
Requires-Dist: pyscagnostics (>=0.1.0a4) ; extra == 'all'
Requires-Dist: pyldavis (>=2.1.2) ; extra == 'all'
Requires-Dist: ray (>=0.8.4) ; extra == 'all'
Requires-Dist: gcsfs (>=0.2.1) ; extra == 'all'
Requires-Dist: google-cloud-storage (>=1.18.0) ; extra == 'all'
Requires-Dist: statsmodels (>=0.10) ; extra == 'all'
Requires-Dist: hdbscan (>=0.8.17) ; extra == 'all'
Requires-Dist: presidio-analyzer (==0.3.8917rc0) ; extra == 'all'
Requires-Dist: gensim (>=3.4.0) ; extra == 'all'
Requires-Dist: nltk (>=3.4) ; extra == 'all'
Requires-Dist: tqdm (>=4.49.0) ; extra == 'all'
Provides-Extra: cluster
Requires-Dist: hdbscan (>=0.8.17) ; extra == 'cluster'
Provides-Extra: gcp
Requires-Dist: gcsfs (>=0.2.1) ; extra == 'gcp'
Requires-Dist: google-cloud-storage (>=1.18.0) ; extra == 'gcp'
Provides-Extra: modin
Requires-Dist: modin (>=0.7.3) ; extra == 'modin'
Requires-Dist: ray (>=0.8.4) ; extra == 'modin'
Provides-Extra: nlp
Requires-Dist: nltk (>=3.4) ; extra == 'nlp'
Requires-Dist: pyldavis (>=2.1.2) ; extra == 'nlp'
Requires-Dist: gensim (>=3.4.0) ; extra == 'nlp'
Requires-Dist: tqdm (>=4.49.0) ; extra == 'nlp'
Provides-Extra: pii
Requires-Dist: presidio-analyzer (==0.3.8917rc0) ; extra == 'pii'
Provides-Extra: scatter
Requires-Dist: pyscagnostics (>=0.1.0a4) ; extra == 'scatter'
Provides-Extra: time
Requires-Dist: statsmodels (>=0.10) ; extra == 'time'
